aifactory/AFAPIClient.py
aifactory/AFAPIServer.py
aifactory/Authentication.py
aifactory/FileUtilities.py
aifactory/__init__.py
aifactory/constants.py
aifactory/Executables/__init__.py
aifactory/Executables/check_version.py
aifactory/Executables/leader_board.py
aifactory/Executables/request_key.py
aifactory/Executables/submit.py
aifactory/ascii_arts/__init__.py
aifactory/ascii_arts/aifactory_logo.py
aifactory/ascii_arts/titles.py
aifactory_alpha-1.2.8.data/scripts/aifactory-leader-board
aifactory_alpha-1.2.8.data/scripts/aifactory-request-key
aifactory_alpha-1.2.8.data/scripts/aifactory-submit
aifactory_easter_eggs/__init__.py
aifactory_easter_eggs/greetings.py
aifactory_alpha-1.2.8.dist-info/METADATA
aifactory_alpha-1.2.8.dist-info/WHEEL
aifactory_alpha-1.2.8.dist-info/top_level.txt
aifactory_alpha-1.2.8.dist-info/RECORD
