Metadata-Version: 2.1
Name: aifactory-alpha
Version: 1.2.8
Summary: alpha version of AI Factory client api package
Home-page: https://www.aifactory.space
Author: yoosunyoung
Author-email: luysunyoung@aifactory.page
License: MIT
Platform: UNKNOWN
Requires-Python: >=3.0
Requires-Dist: pycryptodomex
Requires-Dist: requests
Requires-Dist: pandas
